[
    {
        "domain": ".facebook.com",
        "expirationDate": 1798535533.246095,
        "hostOnly": false,
        "httpOnly": true,
        "name": "ps_l",
        "path": "/",
        "sameSite": "lax",
        "secure": true,
        "session": false,
        "storeId": null,
        "value": "1"
    },
    {
        "domain": ".facebook.com",
        "expirationDate": 1805368426.412147,
        "hostOnly": false,
        "httpOnly": true,
        "name": "datr",
        "path": "/",
        "sameSite": "no_restriction",
        "secure": true,
        "session": false,
        "storeId": null,
        "value": "VCEkae9lpElREOSO0W16ORkW"
    },
    {
        "domain": ".facebook.com",
        "expirationDate": 1780494455.795023,
        "hostOnly": false,
        "httpOnly": true,
        "name": "fr",
        "path": "/",
        "sameSite": "no_restriction",
        "secure": true,
        "session": false,
        "storeId": null,
        "value": "1tTxOzeiQn0OMRhp1.AWcMaICuTSeHrPyyHKkZhTb-3xZLlA1HNdPWMkJQOFbNGgVY6fI.BpqYl3..AAA.0.0.BpqYl3.AWeGfvtFmnc6q4Vbt7z7wPza8g0"
    },
    {
        "domain": ".facebook.com",
        "expirationDate": 1804254455.795308,
        "hostOnly": false,
        "httpOnly": true,
        "name": "xs",
        "path": "/",
        "sameSite": "no_restriction",
        "secure": true,
        "session": false,
        "storeId": null,
        "value": "23%3AIXPQ5d8szjNUSg%3A2%3A1772718450%3A-1%3A-1%3A%3AAczI8nlIJ9h106RB7HESKMKsT0Dq2IejlQk4t_gXMw"
    },
    {
        "domain": ".facebook.com",
        "expirationDate": 1804254455.794769,
        "hostOnly": false,
        "httpOnly": false,
        "name": "c_user",
        "path": "/",
        "sameSite": "no_restriction",
        "secure": true,
        "session": false,
        "storeId": null,
        "value": "61578174716340"
    },
    {
        "domain": ".facebook.com",
        "hostOnly": false,
        "httpOnly": false,
        "name": "presence",
        "path": "/",
        "sameSite": null,
        "secure": true,
        "session": true,
        "storeId": null,
        "value": "C%7B%22lm3%22%3A%22g.1291989849057656%22%2C%22t3%22%3A%5B%7B%22o%22%3A0%2C%22i%22%3A%22g.1583892842797270%22%7D%2C%7B%22o%22%3A0%2C%22i%22%3A%22g.9813463395360543%22%7D%2C%7B%22o%22%3A0%2C%22i%22%3A%22g.25585293287820628%22%7D%5D%2C%22utc3%22%3A1772718486993%2C%22v%22%3A1%7D"
    },
    {
        "domain": ".facebook.com",
        "expirationDate": 1773323270,
        "hostOnly": false,
        "httpOnly": false,
        "name": "dpr",
        "path": "/",
        "sameSite": "no_restriction",
        "secure": true,
        "session": false,
        "storeId": null,
        "value": "1.100000023841858"
    },
    {
        "domain": ".facebook.com",
        "expirationDate": 1798535533.246558,
        "hostOnly": false,
        "httpOnly": true,
        "name": "ps_n",
        "path": "/",
        "sameSite": "no_restriction",
        "secure": true,
        "session": false,
        "storeId": null,
        "value": "1"
    },
    {
        "domain": ".facebook.com",
        "expirationDate": 1807278451.792791,
        "hostOnly": false,
        "httpOnly": true,
        "name": "sb",
        "path": "/",
        "sameSite": "no_restriction",
        "secure": true,
        "session": false,
        "storeId": null,
        "value": "VCEkaWAk2Eej_j623vBSEOw_"
    },
    {
        "domain": ".facebook.com",
        "expirationDate": 1773323270,
        "hostOnly": false,
        "httpOnly": false,
        "name": "wd",
        "path": "/",
        "sameSite": "lax",
        "secure": true,
        "session": false,
        "storeId": null,
        "value": "1746x786"
    }
]
