[
    {
        "domain": ".facebook.com",
        "expirationDate": 1798535533.246095,
        "hostOnly": false,
        "httpOnly": true,
        "name": "ps_l",
        "path": "/",
        "sameSite": "lax",
        "secure": true,
        "session": false,
        "storeId": null,
        "value": "1"
    },
    {
        "domain": ".facebook.com",
        "expirationDate": 1798535506.286518,
        "hostOnly": false,
        "httpOnly": true,
        "name": "datr",
        "path": "/",
        "sameSite": "no_restriction",
        "secure": true,
        "session": false,
        "storeId": null,
        "value": "VCEkae9lpElREOSO0W16ORkW"
    },
    {
        "domain": ".facebook.com",
        "expirationDate": 1775803848.303847,
        "hostOnly": false,
        "httpOnly": true,
        "name": "fr",
        "path": "/",
        "sameSite": "no_restriction",
        "secure": true,
        "session": false,
        "storeId": null,
        "value": "1DD7IJlXK9nc1mTDz.AWfAPJHub8CDsSFQM60YkGeU5KpVvtFDd6zKuTLR-Ve8inpu-Ec.BpYfbH..AAA.0.0.BpYfbH.AWeY1u1f8GS5gk94ILRfd2OBuvI"
    },
    {
        "domain": ".facebook.com",
        "expirationDate": 1799563848.304036,
        "hostOnly": false,
        "httpOnly": true,
        "name": "xs",
        "path": "/",
        "sameSite": "no_restriction",
        "secure": true,
        "session": false,
        "storeId": null,
        "value": "30%3ATbJ8wS9UgGponQ%3A2%3A1768027841%3A-1%3A-1%3A%3AAczNV2wQzrPJwg74jbwHMzKlCqurKmLv8VxUPrLpyQ"
    },
    {
        "domain": ".facebook.com",
        "expirationDate": 1799563848.303569,
        "hostOnly": false,
        "httpOnly": false,
        "name": "c_user",
        "path": "/",
        "sameSite": "no_restriction",
        "secure": true,
        "session": false,
        "storeId": null,
        "value": "100092237443707"
    },
    {
        "domain": ".facebook.com",
        "expirationDate": 1768632650,
        "hostOnly": false,
        "httpOnly": false,
        "name": "dpr",
        "path": "/",
        "sameSite": "no_restriction",
        "secure": true,
        "session": false,
        "storeId": null,
        "value": "1.100000023841858"
    },
    {
        "domain": ".facebook.com",
        "expirationDate": 1798535533.246558,
        "hostOnly": false,
        "httpOnly": true,
        "name": "ps_n",
        "path": "/",
        "sameSite": "no_restriction",
        "secure": true,
        "session": false,
        "storeId": null,
        "value": "1"
    },
    {
        "domain": ".facebook.com",
        "expirationDate": 1802587841.520498,
        "hostOnly": false,
        "httpOnly": true,
        "name": "sb",
        "path": "/",
        "sameSite": "no_restriction",
        "secure": true,
        "session": false,
        "storeId": null,
        "value": "VCEkaWAk2Eej_j623vBSEOw_"
    },
    {
        "domain": ".facebook.com",
        "expirationDate": 1768632650,
        "hostOnly": false,
        "httpOnly": false,
        "name": "wd",
        "path": "/",
        "sameSite": "lax",
        "secure": true,
        "session": false,
        "storeId": null,
        "value": "1746x786"
    }
]
