[
    {
        "domain": ".facebook.com",
        "expirationDate": 1813053977.517058,
        "hostOnly": false,
        "httpOnly": true,
        "name": "ps_l",
        "path": "/",
        "sameSite": "lax",
        "secure": true,
        "session": false,
        "storeId": null,
        "value": "1"
    },
    {
        "domain": ".facebook.com",
        "expirationDate": 1812793732.895269,
        "hostOnly": false,
        "httpOnly": true,
        "name": "datr",
        "path": "/",
        "sameSite": "no_restriction",
        "secure": true,
        "session": false,
        "storeId": null,
        "value": "mrH9aUpP9v_TSSY6Xe7pvHB-"
    },
    {
        "domain": ".facebook.com",
        "expirationDate": 1791966247.203407,
        "hostOnly": false,
        "httpOnly": true,
        "name": "fr",
        "path": "/",
        "sameSite": "no_restriction",
        "secure": true,
        "session": false,
        "storeId": null,
        "value": "19S3nGlC81gmebFnR.AWcb1_-EpY6eTpmoEutAqxpxQl8N4smUe_sDlccO04K6uRxdkW8.BqWJUm..AAA.0.0.BqWJU_.AWcEJffKJpxy5J4D2oLTr2RbsJ8"
    },
    {
        "domain": ".facebook.com",
        "expirationDate": 1789142999,
        "hostOnly": false,
        "httpOnly": false,
        "name": "vpd",
        "path": "/",
        "sameSite": "lax",
        "secure": true,
        "session": false,
        "storeId": null,
        "value": "v1%3B915x412x2.6249999552965164"
    },
    {
        "domain": ".facebook.com",
        "expirationDate": 1815726221.915438,
        "hostOnly": false,
        "httpOnly": true,
        "name": "xs",
        "path": "/",
        "sameSite": "no_restriction",
        "secure": true,
        "session": false,
        "storeId": null,
        "value": "14%3AbbgiFFlMU9goNw%3A2%3A1784190239%3A-1%3A-1%3A%3AAcxbUE6b3KQ7AaXEpzjAiZ03PT48TzxNQr0Yyf0LDQ"
    },
    {
        "domain": ".facebook.com",
        "expirationDate": 1784563796.325871,
        "hostOnly": false,
        "httpOnly": false,
        "name": "locale",
        "path": "/",
        "sameSite": "no_restriction",
        "secure": true,
        "session": false,
        "storeId": null,
        "value": "en_US"
    },
    {
        "domain": ".facebook.com",
        "expirationDate": 1815726221.914321,
        "hostOnly": false,
        "httpOnly": false,
        "name": "c_user",
        "path": "/",
        "sameSite": "no_restriction",
        "secure": true,
        "session": false,
        "storeId": null,
        "value": "61587757155495"
    },
    {
        "domain": ".facebook.com",
        "expirationDate": 1784795045,
        "hostOnly": false,
        "httpOnly": false,
        "name": "dpr",
        "path": "/",
        "sameSite": "no_restriction",
        "secure": true,
        "session": false,
        "storeId": null,
        "value": "1.2374999523162842"
    },
    {
        "domain": ".facebook.com",
        "expirationDate": 1818518996.326159,
        "hostOnly": false,
        "httpOnly": true,
        "name": "pas",
        "path": "/",
        "sameSite": "lax",
        "secure": true,
        "session": false,
        "storeId": null,
        "value": "61587757155495%3AWBwguJ2x5a"
    },
    {
        "domain": ".facebook.com",
        "expirationDate": 1813053977.517845,
        "hostOnly": false,
        "httpOnly": true,
        "name": "ps_n",
        "path": "/",
        "sameSite": "no_restriction",
        "secure": true,
        "session": false,
        "storeId": null,
        "value": "1"
    },
    {
        "domain": ".facebook.com",
        "expirationDate": 1818750217.767516,
        "hostOnly": false,
        "httpOnly": true,
        "name": "sb",
        "path": "/",
        "sameSite": "no_restriction",
        "secure": true,
        "session": false,
        "storeId": null,
        "value": "mrH9aY_F1ZYW5804CuFwhtgu"
    },
    {
        "domain": ".facebook.com",
        "expirationDate": 1784795021,
        "hostOnly": false,
        "httpOnly": false,
        "name": "wd",
        "path": "/",
        "sameSite": "lax",
        "secure": true,
        "session": false,
        "storeId": null,
        "value": "1552x690"
    },
    {
        "domain": ".facebook.com",
        "expirationDate": 1791734998,
        "hostOnly": false,
        "httpOnly": false,
        "name": "wl_cbv",
        "path": "/",
        "sameSite": "no_restriction",
        "secure": true,
        "session": false,
        "storeId": null,
        "value": "v2%3Bclient_version%3A3214%3Btimestamp%3A1783959015"
    }
]
