[
    {
        "domain": ".facebook.com",
        "expirationDate": 1791470959.638956,
        "hostOnly": false,
        "httpOnly": true,
        "name": "ps_l",
        "path": "/",
        "sameSite": "lax",
        "secure": true,
        "session": false,
        "storeId": null,
        "value": "1"
    },
    {
        "domain": ".facebook.com",
        "expirationDate": 1797628454.467026,
        "hostOnly": false,
        "httpOnly": true,
        "name": "datr",
        "path": "/",
        "sameSite": "no_restriction",
        "secure": true,
        "session": false,
        "storeId": null,
        "value": "LEoWaax04C3EZcy0Hc4lsykg"
    },
    {
        "domain": ".facebook.com",
        "expirationDate": 1771257464.088633,
        "hostOnly": false,
        "httpOnly": true,
        "name": "fr",
        "path": "/",
        "sameSite": "no_restriction",
        "secure": true,
        "session": false,
        "storeId": null,
        "value": "1IpPoysrvg78lSTND.AWdrC_Qg0Atx5CTufYzS0u60k2SqQXxV4lfkHiFRm72hmrnCBEg.BpHJd4..AAA.0.0.BpHJd6.AWctinMAOYpoER_ejjPBQyLXZ30"
    },
    {
        "domain": ".facebook.com",
        "expirationDate": 1795017461.481684,
        "hostOnly": false,
        "httpOnly": true,
        "name": "xs",
        "path": "/",
        "sameSite": "no_restriction",
        "secure": true,
        "session": false,
        "storeId": null,
        "value": "35%3A0UJtWoFyFhlK1Q%3A2%3A1763481459%3A-1%3A-1%3A%3AAczNGA2Uyxcd29NBCmZ6iJFvlCBzEUK4E_eZSnzQtw"
    },
    {
        "domain": ".facebook.com",
        "expirationDate": 1795017461.480722,
        "hostOnly": false,
        "httpOnly": false,
        "name": "c_user",
        "path": "/",
        "sameSite": "no_restriction",
        "secure": true,
        "session": false,
        "storeId": null,
        "value": "61550649372068"
    },
    {
        "domain": ".facebook.com",
        "hostOnly": false,
        "httpOnly": false,
        "name": "presence",
        "path": "/",
        "sameSite": null,
        "secure": true,
        "session": true,
        "storeId": null,
        "value": "C%7B%22t3%22%3A%5B%5D%2C%22utc3%22%3A1763481471981%2C%22v%22%3A1%7D"
    },
    {
        "domain": ".facebook.com",
        "expirationDate": 1764086271,
        "hostOnly": false,
        "httpOnly": false,
        "name": "dpr",
        "path": "/",
        "sameSite": "no_restriction",
        "secure": true,
        "session": false,
        "storeId": null,
        "value": "1.100000023841858"
    },
    {
        "domain": ".facebook.com",
        "expirationDate": 1791470959.639103,
        "hostOnly": false,
        "httpOnly": true,
        "name": "ps_n",
        "path": "/",
        "sameSite": "no_restriction",
        "secure": true,
        "session": false,
        "storeId": null,
        "value": "1"
    },
    {
        "domain": ".facebook.com",
        "expirationDate": 1798041458.143393,
        "hostOnly": false,
        "httpOnly": true,
        "name": "sb",
        "path": "/",
        "sameSite": "no_restriction",
        "secure": true,
        "session": false,
        "storeId": null,
        "value": "hSG4aCVkY_E8VromjdndZgjX"
    },
    {
        "domain": ".facebook.com",
        "expirationDate": 1764086271,
        "hostOnly": false,
        "httpOnly": false,
        "name": "wd",
        "path": "/",
        "sameSite": "lax",
        "secure": true,
        "session": false,
        "storeId": null,
        "value": "1746x786"
    }
]
