[
    {
        "domain": ".facebook.com",
        "expirationDate": 1812550144.24771,
        "hostOnly": false,
        "httpOnly": true,
        "name": "ps_l",
        "path": "/",
        "sameSite": "lax",
        "secure": true,
        "session": false,
        "storeId": null,
        "value": "1"
    },
    {
        "domain": ".facebook.com",
        "expirationDate": 1812461448.730124,
        "hostOnly": false,
        "httpOnly": true,
        "name": "datr",
        "path": "/",
        "sameSite": "no_restriction",
        "secure": true,
        "session": false,
        "storeId": null,
        "value": "l5_4aaGBMS2bYzvAF8Rvo6n3"
    },
    {
        "domain": ".facebook.com",
        "expirationDate": 1790007279.597566,
        "hostOnly": false,
        "httpOnly": true,
        "name": "fr",
        "path": "/",
        "sameSite": "no_restriction",
        "secure": true,
        "session": false,
        "storeId": null,
        "value": "1tTLzLl5opVyZ5wcz.AWdBQE1kjTD_441JZJocM1RgMn5e3433MZp6PrjvBrVXlrO6o1E.BqOrD7..AAA.0.0.BqOrD7.AWfBcBzXJdF8nCEbBGAOM2oXiJI"
    },
    {
        "domain": ".facebook.com",
        "expirationDate": 1813767279.597789,
        "hostOnly": false,
        "httpOnly": true,
        "name": "xs",
        "path": "/",
        "sameSite": "no_restriction",
        "secure": true,
        "session": false,
        "storeId": null,
        "value": "15%3AEjPyQOtcbkbwVQ%3A2%3A1782231275%3A-1%3A-1%3A%3AAcwSQZ-2bKPrAohlweZRcWQ8drbwUqy1v5NiUnGVHQ"
    },
    {
        "domain": ".facebook.com",
        "expirationDate": 1813767279.597222,
        "hostOnly": false,
        "httpOnly": false,
        "name": "c_user",
        "path": "/",
        "sameSite": "no_restriction",
        "secure": true,
        "session": false,
        "storeId": null,
        "value": "61586378471858"
    },
    {
        "domain": ".facebook.com",
        "hostOnly": false,
        "httpOnly": false,
        "name": "presence",
        "path": "/",
        "sameSite": null,
        "secure": true,
        "session": true,
        "storeId": null,
        "value": "C%7B%22lm3%22%3A%22g.1583892842797270%22%2C%22t3%22%3A%5B%7B%22o%22%3A0%2C%22i%22%3A%22g.5129138507209614%22%7D%2C%7B%22o%22%3A0%2C%22i%22%3A%22g.1886979832162154%22%7D%2C%7B%22o%22%3A0%2C%22i%22%3A%22g.1733497844305930%22%7D%5D%2C%22utc3%22%3A1782231442573%2C%22v%22%3A1%7D"
    },
    {
        "domain": ".facebook.com",
        "expirationDate": 1782836093,
        "hostOnly": false,
        "httpOnly": false,
        "name": "dpr",
        "path": "/",
        "sameSite": "no_restriction",
        "secure": true,
        "session": false,
        "storeId": null,
        "value": "1.03125"
    },
    {
        "domain": ".facebook.com",
        "expirationDate": 1812550144.248467,
        "hostOnly": false,
        "httpOnly": true,
        "name": "ps_n",
        "path": "/",
        "sameSite": "no_restriction",
        "secure": true,
        "session": false,
        "storeId": null,
        "value": "1"
    },
    {
        "domain": ".facebook.com",
        "expirationDate": 1816791264.978217,
        "hostOnly": false,
        "httpOnly": true,
        "name": "sb",
        "path": "/",
        "sameSite": "no_restriction",
        "secure": true,
        "session": false,
        "storeId": null,
        "value": "l5_4aXWbM91uiZnSKokdbkjb"
    },
    {
        "domain": ".facebook.com",
        "expirationDate": 1782836093,
        "hostOnly": false,
        "httpOnly": false,
        "name": "wd",
        "path": "/",
        "sameSite": "lax",
        "secure": true,
        "session": false,
        "storeId": null,
        "value": "1863x874"
    }
]
